{"address1": "160 South Craig Place", "city": "Lombard", "state": "IL", "zip": "60148", "country": "United States", "phone": "(217) 615-1216", "website": "https://www.wtmau.com", "industry": "Shell Companies", "industryDisp": "Shell Companies", "sector": "Financial Services", "longBusinessSummary": "Welsbach Technology Metals Acquisition Corp. does not have significant operations. The company focuses on effecting a merger, stock exchange, asset acquisition, stock purchase, reorganization, or similar business combination with one or more businesses. It intends to focus on the technology metals and energy transition metals sectors. Welsbach Technology Metals Acquisition Corp. was incorporated in 2021 and is based in Lombard, Illinois.", "companyOfficers": [{"maxAge": 1, "name": "Mr. Daniel Mamadou Blanco B.A., M.Sc.", "age": 50, "title": "CEO & Chairman", "yearBorn": 1972, "exercisedValue": 0, "unexercisedValue": 0}, {"maxAge": 1, "name": "Mr. John  Stanfield CPA", "age": 41, "title": "Chief Financial Officer", "yearBorn": 1981, "exercisedValue": 0, "unexercisedValue": 0}, {"maxAge": 1, "name": "Mr. Christopher J.  Clower", "age": 57, "title": "COO & Director", "yearBorn": 1965, "exercisedValue": 0, "unexercisedValue": 0}], "maxAge": 86400}